{
  "2110-10107": {
    "title": "An Unconstrained Convex Formulation of Compliant Contact",
    "authors": [
      "Alejandro M. Castro",
      "Frank Permenter",
      "Xuchen Han"
    ],
    "submission_date": "2021-10-19",
    "revised_dates": [],
    "doi": "10.1109/TRO.2022.3209077",
    "arxiv_id": "2110.10107",
    "venue": "IEEE Transactions on robotics",
    "year": 2021
  },
  "2110-04157": {
    "title": "Velocity Level Approximation of Pressure Field Contact Patches",
    "authors": [
      "Joseph G. Masterjohn",
      "Damrong Guoy",
      "J. Shepherd",
      "Alejandro M. Castro"
    ],
    "submission_date": "2021-10-08",
    "revised_dates": [],
    "doi": "10.1109/LRA.2022.3203845",
    "arxiv_id": "2110.04157",
    "venue": "IEEE Robotics and Automation Letters",
    "year": 2021
  },
  "2105-01767": {
    "title": "Challenges and Outlook in Robotic Manipulation of Deformable Objects",
    "authors": [
      "Jihong Zhu",
      "A. Cherubini",
      "C. Dune",
      "D. Navarro-Alarcón",
      "Farshid Alambeigi",
      "D. Berenson",
      "F. Ficuciello",
      "K. Harada",
      "Jens Kober",
      "Xiang Li",
      "Jia Pan",
      "Wenzhen Yuan",
      "M. Gienger"
    ],
    "submission_date": "2021-05-04",
    "revised_dates": [],
    "doi": "10.1109/MRA.2022.3147415",
    "arxiv_id": "2105.01767",
    "venue": "IEEE robotics & automation magazine",
    "year": 2021
  },
  "2012-13184": {
    "title": "Simulation of Vision-based Tactile Sensors using Physics based Rendering",
    "authors": [
      "A. Agarwal",
      "Tim Man",
      "Wenzhen Yuan"
    ],
    "submission_date": "2020-12-24",
    "revised_dates": [],
    "doi": "10.1109/ICRA48506.2021.9561122",
    "arxiv_id": "2012.13184",
    "venue": "IEEE International Conference on Robotics and Automation",
    "year": 2020
  },
  "2011-07215": {
    "title": "SoftGym: Benchmarking Deep Reinforcement Learning for Deformable Object Manipulation",
    "authors": [
      "Xingyu Lin",
      "Yufei Wang",
      "Jake Olkin",
      "David Held"
    ],
    "submission_date": "2020-11-14",
    "revised_dates": [],
    "arxiv_id": "2011.07215",
    "venue": "Conference on Robot Learning",
    "year": 2020
  },
  "2004-03691": {
    "title": "Soft-bubble grippers for robust and perceptive manipulation",
    "authors": [
      "N. Kuppuswamy",
      "A. Alspach",
      "Avinash Uttamchandani",
      "Sam Creasey",
      "Takuya Ikeda",
      "Russ Tedrake"
    ],
    "submission_date": "2020-04-07",
    "revised_dates": [],
    "doi": "10.1109/IROS45743.2020.9341534",
    "arxiv_id": "2004.03691",
    "venue": "IEEE/RJS International Conference on Intelligent RObots and Systems",
    "year": 2020
  },
  "1907-04587": {
    "title": "Non-smooth Newton Methods for Deformable Multi-body Dynamics",
    "authors": [
      "M. Macklin",
      "Kenny Erleben",
      "Matthias Müller",
      "N. Chentanez",
      "S. Jeschke",
      "Viktor Makoviychuk"
    ],
    "submission_date": "2019-07-10",
    "revised_dates": [],
    "doi": "10.1145/3338695",
    "arxiv_id": "1907.04587",
    "venue": "ACM Transactions on Graphics",
    "year": 2019
  }
}