{
  "2211-10439": {
    "title": "BEVFormer v2: Adapting Modern Image Backbones to Bird's-Eye-View Recognition via Perspective Supervision",
    "authors": [
      "Chenyu Yang",
      "Yuntao Chen",
      "Haofei Tian",
      "Chenxin Tao",
      "Xizhou Zhu",
      "Zhaoxiang Zhang",
      "Gao Huang",
      "Hongyang Li",
      "Y. Qiao",
      "Lewei Lu",
      "Jie Zhou",
      "Jifeng Dai"
    ],
    "submission_date": "2022-11-18",
    "revised_dates": [],
    "doi": "10.1109/CVPR52729.2023.01710",
    "arxiv_id": "2211.10439",
    "venue": "Computer Vision and Pattern Recognition",
    "year": 2022
  },
  "2209-08575": {
    "title": "SegNeXt: Rethinking Convolutional Attention Design for Semantic Segmentation",
    "authors": [
      "Meng-Hao Guo",
      "Chenggang Lu",
      "Qibin Hou",
      "Zheng Liu",
      "Ming-Ming Cheng",
      "Shiyong Hu"
    ],
    "submission_date": "2022-09-18",
    "revised_dates": [],
    "doi": "10.48550/arXiv.2209.08575",
    "arxiv_id": "2209.08575",
    "venue": "Neural Information Processing Systems",
    "year": 2022
  },
  "2207-11860": {
    "title": "Behind Every Domain There is a Shift: Adapting Distortion-Aware Vision Transformers for Panoramic Semantic Segmentation",
    "authors": [
      "Jiaming Zhang",
      "Kailun Yang",
      "Haowen Shi",
      "Simon Reiß",
      "Kunyu Peng",
      "Chaoxiang Ma",
      "Haodong Fu",
      "Kaiwei Wang",
      "R. Stiefelhagen"
    ],
    "submission_date": "2022-07-25",
    "revised_dates": [],
    "doi": "10.1109/TPAMI.2024.3408642",
    "arxiv_id": "2207.11860",
    "venue": "IEEE Transactions on Pattern Analysis and Machine Intelligence",
    "year": 2022
  },
  "2207-06205": {
    "title": "Trans4Map: Revisiting Holistic Bird’s-Eye-View Mapping from Egocentric Images to Allocentric Semantics with Vision Transformers",
    "authors": [
      "Chang Chen",
      "Jiaming Zhang",
      "Kailun Yang",
      "Kunyu Peng",
      "R. Stiefelhagen"
    ],
    "submission_date": "2022-07-13",
    "revised_dates": [],
    "doi": "10.1109/WACV56688.2023.00400",
    "arxiv_id": "2207.06205",
    "venue": "IEEE Workshop/Winter Conference on Applications of Computer Vision",
    "year": 2022
  },
  "2207-02437": {
    "title": "Complementary Bi-directional Feature Compression for Indoor 360° Semantic Segmentation with Self-distillation",
    "authors": [
      "Zishuo Zheng",
      "Chunyu Lin",
      "Lang Nie",
      "K. Liao",
      "Zhijie Shen",
      "Yao Zhao"
    ],
    "submission_date": "2022-07-06",
    "revised_dates": [],
    "doi": "10.1109/WACV56688.2023.00448",
    "arxiv_id": "2207.02437",
    "venue": "IEEE Workshop/Winter Conference on Applications of Computer Vision",
    "year": 2022
  },
  "2205-02833": {
    "title": "Cross-view Transformers for real-time Map-view Semantic Segmentation",
    "authors": [
      "Brady Zhou",
      "Philipp Krahenbuhl"
    ],
    "submission_date": "2022-05-05",
    "revised_dates": [],
    "doi": "10.1109/CVPR52688.2022.01339",
    "arxiv_id": "2205.02833",
    "venue": "Computer Vision and Pattern Recognition",
    "year": 2022
  },
  "2203-17270": {
    "title": "BEVFormer: Learning Bird's-Eye-View Representation from Multi-Camera Images via Spatiotemporal Transformers",
    "authors": [
      "Zhiqi Li",
      "Wenhai Wang",
      "Hongyang Li",
      "Enze Xie",
      "Chonghao Sima",
      "Tong Lu",
      "Qiao Yu",
      "Jifeng Dai"
    ],
    "submission_date": "2022-03-31",
    "revised_dates": [],
    "doi": "10.48550/arXiv.2203.17270",
    "arxiv_id": "2203.17270",
    "venue": "European Conference on Computer Vision",
    "year": 2022
  },
  "2203-05625": {
    "title": "PETR: Position Embedding Transformation for Multi-View 3D Object Detection",
    "authors": [
      "Yingfei Liu",
      "Tiancai Wang",
      "X. Zhang",
      "Jian Sun"
    ],
    "submission_date": "2022-03-10",
    "revised_dates": [],
    "doi": "10.48550/arXiv.2203.05625",
    "arxiv_id": "2203.05625",
    "venue": "European Conference on Computer Vision",
    "year": 2022
  },
  "2203-04050": {
    "title": "BEVSegFormer: Bird's Eye View Semantic Segmentation From Arbitrary Camera Rigs",
    "authors": [
      "Lang Peng",
      "Zhirong Chen",
      "Zhang-Hua Fu",
      "Pengpeng Liang",
      "Erkang Cheng"
    ],
    "submission_date": "2022-03-08",
    "revised_dates": [],
    "doi": "10.1109/WACV56688.2023.00588",
    "arxiv_id": "2203.04050",
    "venue": "IEEE Workshop/Winter Conference on Applications of Computer Vision",
    "year": 2022
  },
  "2203-01452": {
    "title": "Bending Reality: Distortion-aware Transformers for Adapting to Panoramic Semantic Segmentation",
    "authors": [
      "Jiaming Zhang",
      "Kailun Yang",
      "Chaoxiang Ma",
      "Simon Reiß",
      "Kunyu Peng",
      "R. Stiefelhagen"
    ],
    "submission_date": "2022-03-02",
    "revised_dates": [],
    "doi": "10.1109/CVPR52688.2022.01641",
    "arxiv_id": "2203.01452",
    "venue": "Computer Vision and Pattern Recognition",
    "year": 2022
  },
  "2107-03172": {
    "title": "Trans4Trans: Efficient Transformer for Transparent Object Segmentation to Help Visually Impaired People Navigate in the Real World",
    "authors": [
      "Jiaming Zhang",
      "Kailun Yang",
      "Angela Constantinescu",
      "Kunyu Peng",
      "Karin Müller",
      "R. Stiefelhagen"
    ],
    "submission_date": "2021-07-07",
    "revised_dates": [],
    "doi": "10.1109/ICCVW54120.2021.00202",
    "arxiv_id": "2107.03172",
    "venue": "2021 IEEE/CVF International Conference on Computer Vision Workshops (ICCVW)",
    "year": 2021
  },
  "2109-02749": {
    "title": "Pano3D: A Holistic Benchmark and a Solid Baseline for 360° Depth Estimation",
    "authors": [
      "G. Albanis",
      "N. Zioulis",
      "Petros Drakoulis",
      "V. Gkitsas",
      "V. Sterzentsenko",
      "Federico Álvarez",
      "D. Zarpalas",
      "P. Daras"
    ],
    "submission_date": "2021-06-01",
    "revised_dates": [],
    "doi": "10.1109/CVPRW53098.2021.00413",
    "arxiv_id": "2109.02749",
    "venue": "2021 IEEE/CVF Conference on Computer Vision and Pattern Recognition Workshops (CVPRW)",
    "year": 2021
  },
  "2105-15203": {
    "title": "SegFormer: Simple and Efficient Design for Semantic Segmentation with Transformers",
    "authors": [
      "Enze Xie",
      "Wenhai Wang",
      "Zhiding Yu",
      "Anima Anandkumar",
      "J. Álvarez",
      "Ping Luo"
    ],
    "submission_date": "2021-05-31",
    "revised_dates": [],
    "arxiv_id": "2105.15203",
    "venue": "Neural Information Processing Systems",
    "year": 2021
  },
  "2104-08683": {
    "title": "Self-Supervised Pillar Motion Learning for Autonomous Driving",
    "authors": [
      "Chenxu Luo",
      "Xiaodong Yang",
      "A. Yuille"
    ],
    "submission_date": "2021-04-18",
    "revised_dates": [],
    "doi": "10.1109/CVPR46437.2021.00320",
    "arxiv_id": "2104.08683",
    "venue": "Computer Vision and Pattern Recognition",
    "year": 2021
  },
  "2011-11498": {
    "title": "HoHoNet: 360 Indoor Holistic Understanding with Latent Horizontal Features",
    "authors": [
      "Cheng Sun",
      "Min Sun",
      "Hwann-Tzong Chen"
    ],
    "submission_date": "2020-11-23",
    "revised_dates": [],
    "doi": "10.1109/CVPR46437.2021.00260",
    "arxiv_id": "2011.11498",
    "venue": "Computer Vision and Pattern Recognition",
    "year": 2020
  },
  "2010-04159": {
    "title": "Deformable DETR: Deformable Transformers for End-to-End Object Detection",
    "authors": [
      "Xizhou Zhu",
      "Weijie Su",
      "Lewei Lu",
      "Bin Li",
      "Xiaogang Wang",
      "Jifeng Dai"
    ],
    "submission_date": "2020-10-08",
    "revised_dates": [],
    "arxiv_id": "2010.04159",
    "venue": "International Conference on Learning Representations",
    "year": 2020
  },
  "2010-01191": {
    "title": "Semantic MapNet: Building Allocentric SemanticMaps and Representations from Egocentric Views",
    "authors": [
      "Vincent Cartillier",
      "Zhile Ren",
      "Neha Jain",
      "Stefan Lee",
      "Irfan Essa",
      "Dhruv Batra"
    ],
    "submission_date": "2020-10-02",
    "revised_dates": [],
    "doi": "10.1609/aaai.v35i2.16180",
    "arxiv_id": "2010.01191",
    "venue": "AAAI Conference on Artificial Intelligence",
    "year": 2020
  },
  "2008-01179": {
    "title": "PillarFlow: End-to-end Birds-eye-view Flow Estimation for Autonomous Driving",
    "authors": [
      "Kuan-Hui Lee",
      "Matthew Kliemann",
      "Adrien Gaidon",
      "Jie Li",
      "Chao Fang",
      "Sudeep Pillai",
      "Wolfram Burgard"
    ],
    "submission_date": "2020-08-03",
    "revised_dates": [],
    "doi": "10.1109/IROS45743.2020.9340931",
    "arxiv_id": "2008.01179",
    "venue": "IEEE/RJS International Conference on Intelligent RObots and Systems",
    "year": 2020
  },
  "2006-10731": {
    "title": "Spin-Weighted Spherical CNNs",
    "authors": [
      "Carlos Esteves",
      "A. Makadia",
      "Kostas Daniilidis"
    ],
    "submission_date": "2020-06-18",
    "revised_dates": [],
    "arxiv_id": "2006.10731",
    "venue": "Neural Information Processing Systems",
    "year": 2020
  },
  "1912-09390": {
    "title": "Tangent Images for Mitigating Spherical Distortion",
    "authors": [
      "Marc Eder",
      "Mykhailo Shvets",
      "John Lim",
      "Jan-Michael Frahm"
    ],
    "submission_date": "2019-12-19",
    "revised_dates": [],
    "doi": "10.1109/cvpr42600.2020.01244",
    "arxiv_id": "1912.09390",
    "venue": "Computer Vision and Pattern Recognition",
    "year": 2019
  },
  "1909-11065": {
    "title": "Object-Contextual Representations for Semantic Segmentation",
    "authors": [
      "Yuhui Yuan",
      "Xilin Chen",
      "Jingdong Wang"
    ],
    "submission_date": "2019-09-24",
    "revised_dates": [],
    "doi": "10.1007/978-3-030-58539-6_11",
    "arxiv_id": "1909.11065",
    "venue": "European Conference on Computer Vision",
    "year": 2019
  },
  "1909-08112": {
    "title": "Spherical View Synthesis for Self-Supervised 360° Depth Estimation",
    "authors": [
      "N. Zioulis",
      "Antonis Karakottas",
      "D. Zarpalas",
      "Federico Álvarez",
      "P. Daras"
    ],
    "submission_date": "2019-09-01",
    "revised_dates": [],
    "doi": "10.1109/3DV.2019.00081",
    "arxiv_id": "1909.08112",
    "venue": "International Conference on 3D Vision",
    "year": 2019
  },
  "1908-07919": {
    "title": "Deep High-Resolution Representation Learning for Visual Recognition",
    "authors": [
      "Jingdong Wang",
      "Ke Sun",
      "Tianheng Cheng",
      "Borui Jiang",
      "Chaorui Deng",
      "Yang Zhao",
      "Dong Liu",
      "Yadong Mu",
      "Mingkui Tan",
      "Xinggang Wang",
      "Wenyu Liu",
      "Bin Xiao"
    ],
    "submission_date": "2019-08-20",
    "revised_dates": [],
    "doi": "10.1109/TPAMI.2020.2983686",
    "arxiv_id": "1908.07919",
    "venue": "IEEE Transactions on Pattern Analysis and Machine Intelligence",
    "year": 2019
  },
  "1908-00222": {
    "title": "Structured3D: A Large Photo-realistic Dataset for Structured 3D Modeling",
    "authors": [
      "Jia Zheng",
      "Junfei Zhang",
      "Jing Li",
      "Rui Tang",
      "Shenghua Gao",
      "Zihan Zhou"
    ],
    "submission_date": "2019-08-01",
    "revised_dates": [],
    "doi": "10.1007/978-3-030-58545-7_30",
    "arxiv_id": "1908.00222",
    "venue": "European Conference on Computer Vision",
    "year": 2019
  },
  "1907-12849": {
    "title": "Orientation-Aware Semantic Segmentation on Icosahedron Spheres",
    "authors": [
      "Chao Zhang",
      "Stephan Liwicki",
      "William Smith",
      "R. Cipolla"
    ],
    "submission_date": "2019-07-30",
    "revised_dates": [],
    "doi": "10.1109/ICCV.2019.00363",
    "arxiv_id": "1907.12849",
    "venue": "IEEE International Conference on Computer Vision",
    "year": 2019
  },
  "1906-03560": {
    "title": "Cross-View Semantic Segmentation for Sensing Surroundings",
    "authors": [
      "Bowen Pan",
      "Jiankai Sun",
      "Ho Yin Tiga Leung",
      "A. Andonian",
      "Bolei Zhou"
    ],
    "submission_date": "2019-06-09",
    "revised_dates": [],
    "doi": "10.1109/LRA.2020.3004325",
    "arxiv_id": "1906.03560",
    "venue": "IEEE Robotics and Automation Letters",
    "year": 2019
  },
  "1904-03461": {
    "title": "Embodied Question Answering in Photorealistic Environments With Point Cloud Perception",
    "authors": [
      "Erik Wijmans",
      "Samyak Datta",
      "Oleksandr Maksymets",
      "Abhishek Das",
      "Georgia Gkioxari",
      "Stefan Lee",
      "Irfan Essa",
      "Devi Parikh",
      "Dhruv Batra"
    ],
    "submission_date": "2019-04-06",
    "revised_dates": [],
    "doi": "10.1109/CVPR.2019.00682",
    "arxiv_id": "1904.03461",
    "venue": "Computer Vision and Pattern Recognition",
    "year": 2019
  },
  "1904-01201": {
    "title": "Habitat: A Platform for Embodied AI Research",
    "authors": [
      "M. Savva",
      "Abhishek Kadian",
      "Oleksandr Maksymets",
      "Yili Zhao",
      "Erik Wijmans",
      "Bhavana Jain",
      "Julian Straub",
      "Jia Liu",
      "V. Koltun",
      "Jitendra Malik",
      "Devi Parikh",
      "Dhruv Batra"
    ],
    "submission_date": "2019-04-02",
    "revised_dates": [],
    "doi": "10.1109/ICCV.2019.00943",
    "arxiv_id": "1904.01201",
    "venue": "IEEE International Conference on Computer Vision",
    "year": 2019
  },
  "1903-00268": {
    "title": "Volumetric Instance-Aware Semantic Mapping and 3D Object Discovery",
    "authors": [
      "Margarita Grinvald",
      "Fadri Furrer",
      "Tonci Novkovic",
      "Jen Jen Chung",
      "César Cadena",
      "R. Siegwart",
      "Juan I. Nieto"
    ],
    "submission_date": "2019-03-01",
    "revised_dates": [],
    "doi": "10.1109/LRA.2019.2923960",
    "arxiv_id": "1903.00268",
    "venue": "IEEE Robotics and Automation Letters",
    "year": 2019
  },
  "1902-07830": {
    "title": "Deep Multi-Modal Object Detection and Semantic Segmentation for Autonomous Driving: Datasets, Methods, and Challenges",
    "authors": [
      "Di Feng",
      "Christian Haase-Schuetz",
      "Lars Rosenbaum",
      "Heinz Hertlein",
      "Fabian Duffhauss",
      "Claudius Gläser",
      "W. Wiesbeck",
      "K. Dietmayer"
    ],
    "submission_date": "2019-02-21",
    "revised_dates": [],
    "doi": "10.1109/TITS.2020.2972974",
    "arxiv_id": "1902.07830",
    "venue": "IEEE transactions on intelligent transportation systems (Print)",
    "year": 2019
  },
  "1902-04615": {
    "title": "Gauge Equivariant Convolutional Networks and the Icosahedral CNN",
    "authors": [
      "Taco Cohen",
      "Maurice Weiler",
      "Berkay Kicanaoglu",
      "Max Welling"
    ],
    "submission_date": "2019-02-11",
    "revised_dates": [],
    "arxiv_id": "1902.04615",
    "venue": "International Conference on Machine Learning",
    "year": 2019
  },
  "1901-02039": {
    "title": "Spherical CNNs on Unstructured Grids",
    "authors": [
      "Chiyu “Max”",
      "Jiang",
      "Jingwei Huang",
      "K. Kashinath",
      "Lawrence Berkeley Nat’l Lab",
      "P. Marcus",
      "M. Nießner",
      "MeshConv MeshConv"
    ],
    "submission_date": "2019-01-07",
    "revised_dates": [],
    "arxiv_id": "1901.02039",
    "venue": "International Conference on Learning Representations",
    "year": 2019
  },
  "1809-00716": {
    "title": "InteriorNet: Mega-scale Multi-sensor Photo-realistic Indoor Scenes Dataset",
    "authors": [
      "Wenbin Li",
      "Sajad Saeedi",
      "J. McCormac",
      "R. Clark",
      "Dimos Tzoumanikas",
      "Qing Ye",
      "Yuzhong Huang",
      "R. Tang",
      "Stefan Leutenegger"
    ],
    "submission_date": "2018-09-03",
    "revised_dates": [],
    "arxiv_id": "1809.00716",
    "venue": "British Machine Vision Conference",
    "year": 2018
  },
  "1808-10654": {
    "title": "Gibson Env: Real-World Perception for Embodied Agents",
    "authors": [
      "F. Xia",
      "Amir Zamir",
      "Zhi-Yang He",
      "Alexander Sax",
      "Jitendra Malik",
      "S. Savarese"
    ],
    "submission_date": "2018-06-01",
    "revised_dates": [],
    "doi": "10.1109/CVPR.2018.00945",
    "arxiv_id": "1808.10654",
    "venue": "2018 IEEE/CVF Conference on Computer Vision and Pattern Recognition",
    "year": 2018
  },
  "1711-07280": {
    "title": "Vision-and-Language Navigation: Interpreting Visually-Grounded Navigation Instructions in Real Environments",
    "authors": [
      "Peter Anderson",
      "Qi Wu",
      "Damien Teney",
      "Jake Bruce",
      "Mark Johnson",
      "Niko Sünderhauf",
      "I. Reid",
      "Stephen Gould",
      "Anton van den Hengel"
    ],
    "submission_date": "2017-11-20",
    "revised_dates": [],
    "doi": "10.1109/CVPR.2018.00387",
    "arxiv_id": "1711.07280",
    "venue": "2018 IEEE/CVF Conference on Computer Vision and Pattern Recognition",
    "year": 2017
  },
  "1709-06158": {
    "title": "Matterport3D: Learning from RGB-D Data in Indoor Environments",
    "authors": [
      "Angel X. Chang",
      "Angela Dai",
      "T. Funkhouser",
      "Maciej Halber",
      "M. Nießner",
      "M. Savva",
      "Shuran Song",
      "Andy Zeng",
      "Yinda Zhang"
    ],
    "submission_date": "2017-09-18",
    "revised_dates": [],
    "doi": "10.1109/3DV.2017.00081",
    "arxiv_id": "1709.06158",
    "venue": "International Conference on 3D Vision",
    "year": 2017
  },
  "1704-05519": {
    "title": "Computer Vision for Autonomous Vehicles: Problems, Datasets and State-of-the-Art",
    "authors": [
      "J. Janai",
      "F. Güney",
      "Aseem Behl",
      "Andreas Geiger"
    ],
    "submission_date": "2017-04-18",
    "revised_dates": [],
    "doi": "10.1561/0600000079",
    "arxiv_id": "1704.05519",
    "venue": "Foundations and Trends in Computer Graphics and Vision",
    "year": 2017
  },
  "1702-01105": {
    "title": "Joint 2D-3D-Semantic Data for Indoor Scene Understanding",
    "authors": [
      "Iro Armeni",
      "S. Sax",
      "Amir Zamir",
      "S. Savarese"
    ],
    "submission_date": "2017-02-03",
    "revised_dates": [],
    "arxiv_id": "1702.01105",
    "venue": "arXiv.org",
    "year": 2017
  },
  "1612-01105": {
    "title": "Pyramid Scene Parsing Network",
    "authors": [
      "Hengshuang Zhao",
      "Jianping Shi",
      "Xiaojuan Qi",
      "Xiaogang Wang",
      "Jiaya Jia"
    ],
    "submission_date": "2016-12-04",
    "revised_dates": [],
    "doi": "10.1109/CVPR.2017.660",
    "arxiv_id": "1612.01105",
    "venue": "Computer Vision and Pattern Recognition",
    "year": 2016
  }
}