{
  "2012-07429": {
    "title": "Approximate Laplace approximations for scalable model selection",
    "authors": [
      "D. Rossell",
      "Oriol Abril",
      "A. Bhattacharya"
    ],
    "submission_date": "2020-12-14",
    "revised_dates": [],
    "doi": "10.1111/rssb.12466",
    "arxiv_id": "2012.07429",
    "venue": "Journal of the Royal Statistical Society: Series B (Statistical Methodology)",
    "year": 2020
  },
  "2011-02328": {
    "title": "Waste‐free sequential Monte Carlo",
    "authors": [
      "Hai-Dang Dau",
      "N. Chopin"
    ],
    "submission_date": "2020-11-04",
    "revised_dates": [],
    "doi": "10.1111/rssb.12475",
    "arxiv_id": "2011.02328",
    "venue": "Journal of the Royal Statistical Society: Series B (Statistical Methodology)",
    "year": 2020
  },
  "1803-10439": {
    "title": "BIVAS: A Scalable Bayesian Method for Bi-Level Variable Selection With Applications",
    "authors": [
      "Mingxuan Cai",
      "Mingwei Dai",
      "Jingsi Ming",
      "Heng Peng",
      "Jin Liu",
      "Can Yang"
    ],
    "submission_date": "2018-03-28",
    "revised_dates": [],
    "doi": "10.1080/10618600.2019.1624365",
    "arxiv_id": "1803.10439",
    "venue": "Journal of Computational And Graphical Statistics",
    "year": 2018
  },
  "1101-6037": {
    "title": "Sequential Monte Carlo on large binary sampling spaces",
    "authors": [
      "C. Schäfer",
      "N. Chopin"
    ],
    "submission_date": "2011-01-31",
    "revised_dates": [],
    "doi": "10.1007/s11222-011-9299-z",
    "arxiv_id": "1101.6037",
    "venue": "Statistics and computing",
    "year": 2011
  }
}