{
  "1906-04192": {
    "title": "Cation Disorder and Lithium Insertion Mechanism of Wadsley-Roth Crystallographic Shear Phases from First Principles.",
    "authors": [
      "Can P. Koçer",
      "Kent J. Griffith",
      "C. Grey",
      "A. J. Morris"
    ],
    "submission_date": "2019-06-10",
    "revised_dates": [],
    "doi": "10.1021/jacs.9b06316",
    "arxiv_id": "1906.04192",
    "venue": "Journal of the American Chemical Society",
    "year": 2019
  },
  "1803-02802": {
    "title": "Realistic Atomistic Structure of Amorphous Silicon from Machine-Learning-Driven Molecular Dynamics.",
    "authors": [
      "Volker L. Deringer",
      "N. Bernstein",
      "A. Bartók",
      "M. Cliffe",
      "R. Kerber",
      "Lauren E. Marbella",
      "C. Grey",
      "S. Elliott",
      "Gábor Csányi"
    ],
    "submission_date": "2018-03-07",
    "revised_dates": [],
    "doi": "10.1021/acs.jpclett.8b00902",
    "arxiv_id": "1803.02802",
    "venue": "Journal of Physical Chemistry Letters",
    "year": 2018
  }
}